{"code":0,"message":"ok","result":[{"productId":0,"productType":4,"productName":"东方梦工厂 动画你的世界","urllink":"https://study.163.com/topics/201805pearl2","piclink":"http://edu-image.nosdn.127.net/31f92685-e762-4ce0-a58e-138dc2e1f531.jpg?imageView&quality=100","picColor":"#fecc02","searchItemType":16,"actionScene":"SCENE_UNKNOWN","recId":null,"algInfo":null},{"productId":0,"productType":4,"productName":"holy high 青年节！","urllink":"https://study.163.com/topics/holyhigh","piclink":"http://edu-image.nosdn.127.net/16B3D52260800777CD763851412FCFA3.png?imageView&thumbnail=980y340&quality=100","picColor":"#cfdff2","searchItemType":16,"actionScene":"SCENE_UNKNOWN","recId":null,"algInfo":null},{"productId":1001386007,"productType":3,"productName":"Web安全工程师（进阶）","urllink":"https://mooc.study.163.com/smartSpec/detail/1001386007.htm","piclink":"http://edu-image.nosdn.127.net/8ac2c12a-07a9-49ca-b2e2-c2ab83199437.jpg?imageView&quality=100","picColor":"#051522","searchItemType":30,"actionScene":"SCENE_UNKNOWN","recId":null,"algInfo":null},{"productId":0,"productType":4,"productName":"我想和你“好好说话”","urllink":"https://study.163.com/topics/hhsh_web","piclink":"http://edu-image.nosdn.127.net/499c780c-e4d9-4f8d-9450-4775f3dd9158.jpg?imageView&quality=100","picColor":"#ffcc27","searchItemType":16,"actionScene":"SCENE_UNKNOWN","recId":null,"algInfo":null},{"productId":0,"productType":4,"productName":"做人工智能头号玩家","urllink":"https://study.163.com/topics/201804seethefuture","piclink":"http://edu-image.nosdn.127.net/d9b6b90f-24f9-4ae1-95b8-6bfa8f636e22.jpg?imageView&quality=100","picColor":"#0f319c","searchItemType":16,"actionScene":"SCENE_UNKNOWN","recId":null,"algInfo":null},{"productId":0,"productType":4,"productName":"古琴大师班","urllink":"https://study.163.com/topics/guqin_2018_05","piclink":"http://edu-image.nosdn.127.net/82da1e7a-0dd0-460c-bcdf-0d95883d2e05.png?imageView&quality=100","picColor":"#f2f2f0","searchItemType":16,"actionScene":"SCENE_UNKNOWN","recId":null,"algInfo":null},{"productId":0,"productType":5,"productName":"卡搭好作品系列","urllink":"http://163.lu/cELsT2","piclink":"http://edu-image.nosdn.127.net/1ff80faa-bddf-45c8-b5bb-c4f95a0593b4.png?imageView&quality=100","picColor":"#2b3046","searchItemType":16,"actionScene":"SCENE_UNKNOWN","recId":null,"algInfo":null}],"uuid":null}